autologs/__init__.py
autologs/autologs.py
autologs/test_local.py
python_autologs-0.0.5.dist-info/LICENSE
python_autologs-0.0.5.dist-info/METADATA
python_autologs-0.0.5.dist-info/WHEEL
python_autologs-0.0.5.dist-info/top_level.txt
python_autologs-0.0.5.dist-info/RECORD
