Metadata-Version: 2.1
Name: python-autologs
Version: 0.0.5
Summary: Auto generate logs for functions
Home-page: https://github.com/myakove/python-autologs
Author: Meni Yakove
Author-email: myakove@gmail.com
License: UNKNOWN
Platform: UNKNOWN
Classifier: Programming Language :: Python :: 3
Classifier: License :: OSI Approved :: MIT License
Classifier: Operating System :: OS Independent
